smclip/__init__.py
smclip/commands.py
smclip/exceptions.py
smclip/parsers.py
smclip-0.3.0.dist-info/DESCRIPTION.rst
smclip-0.3.0.dist-info/METADATA
smclip-0.3.0.dist-info/RECORD
smclip-0.3.0.dist-info/WHEEL
smclip-0.3.0.dist-info/metadata.json
smclip-0.3.0.dist-info/top_level.txt
