Metadata-Version: 2.0
Name: smclip
Version: 0.3.0
Summary: Simple Multi Command Line Parser
Home-page: https://github.com/vkrizan/python-smclip
Author: Viliam Krizan
Author-email: vkrizan@redhat.com
License: LGPLv3+
Keywords: cli,argument parser,multi commands
Platform: UNKNOWN
Classifier: Development Status :: 4 - Beta
Classifier: Intended Audience :: Developers
Classifier: Topic :: Software Development :: Libraries
Classifier: Topic :: Software Development :: User Interfaces
Classifier: Topic :: Terminals
Classifier: License :: OSI Approved :: GNU Lesser General Public License v3 or later (LGPLv3+)
Classifier: Programming Language :: Python :: 2
Classifier: Programming Language :: Python :: 2.7
Classifier: Programming Language :: Python :: 3
Classifier: Programming Language :: Python :: 3.3
Classifier: Programming Language :: Python :: 3.4
Classifier: Programming Language :: Python :: 3.5
